music_dragon/__init__.py
music_dragon/cache.py
music_dragon/localsongs.py
music_dragon/log.py
music_dragon/main.py
music_dragon/musicbrainz.py
music_dragon/preferences.py
music_dragon/repository.py
music_dragon/utils.py
music_dragon/wiki.py
music_dragon/workers.py
music_dragon/ytcommons.py
music_dragon/ytdownloader.py
music_dragon/ytmusic.py
music_dragon/ui/__init__.py
music_dragon/ui/albumtrackswidget.py
music_dragon/ui/artistalbumswidget.py
music_dragon/ui/clickablelabel.py
music_dragon/ui/clickablewidget.py
music_dragon/ui/downloadswidget.py
music_dragon/ui/imagepreviewwindow.py
music_dragon/ui/listwidgetmodelview.py
music_dragon/ui/localalbumsview.py
music_dragon/ui/localartistsview.py
music_dragon/ui/localsongsview.py
music_dragon/ui/mainwindow.py
music_dragon/ui/preferenceswindow.py
music_dragon/ui/resources.py
music_dragon/ui/searchresultswidget.py
music_dragon/ui/ui_imagepreviewwindow.py
music_dragon/ui/ui_mainwindow.py
music_dragon/ui/ui_preferenceswindow.py
music_dragon/ui/ui_ytmusicsetupwindow.py
music_dragon/ui/ytmusicsetupwindow.py
music_dragon-0.2.dist-info/LICENSE.txt
music_dragon-0.2.dist-info/METADATA
music_dragon-0.2.dist-info/WHEEL
music_dragon-0.2.dist-info/entry_points.txt
music_dragon-0.2.dist-info/top_level.txt
music_dragon-0.2.dist-info/RECORD
