Metadata-Version: 2.1
Name: music-dragon
Version: 0.2
Summary: All-in-one music manager: scrapes albums, artists and songs from musicbrainz and automatically download them from youtube.
Home-page: https://github.com/Docheinstein/music-dragon
Author: Stefano Dottore
Author-email: docheinstein@gmail.com
License: MIT
Keywords: music manager youtube spotify musicbrainz musicbrainzngs tag cover eyed3 ytmusicapi youtube_dl
Requires-Python: >=3
License-File: LICENSE.txt
Requires-Dist: musicbrainzngs
Requires-Dist: youtube-dl
Requires-Dist: ytmusicapi
Requires-Dist: eyed3
Requires-Dist: PyQt5
Requires-Dist: wikidata
Requires-Dist: requests
Requires-Dist: levenshtein
